react_frontend/0025fb26.js
react_frontend/0025fb26.js.LICENSE.txt
react_frontend/0025fb26.js.gz
react_frontend/034f7c4f.js
react_frontend/034f7c4f.js.gz
react_frontend/03c63710.js
react_frontend/03c63710.js.LICENSE.txt
react_frontend/03c63710.js.gz
react_frontend/03d687e8.js
react_frontend/03d687e8.js.gz
react_frontend/0476122e.js
react_frontend/0476122e.js.gz
react_frontend/04906c3f.js
react_frontend/04906c3f.js.gz
react_frontend/0530ab6a.js
react_frontend/0530ab6a.js.gz
react_frontend/060387a7.js
react_frontend/060387a7.js.gz
react_frontend/06138575.js
react_frontend/06138575.js.gz
react_frontend/065c67c9.js
react_frontend/065c67c9.js.LICENSE.txt
react_frontend/065c67c9.js.gz
react_frontend/0780165d.js
react_frontend/0780165d.js.gz
react_frontend/0785756c.js
react_frontend/0785756c.js.gz
react_frontend/083278ec.js
react_frontend/083278ec.js.LICENSE.txt
react_frontend/083278ec.js.gz
react_frontend/09b415b3.js
react_frontend/09b415b3.js.gz
react_frontend/09e4885d.js
react_frontend/09e4885d.js.LICENSE.txt
react_frontend/09e4885d.js.gz
react_frontend/0c0614f4.js
react_frontend/0c0614f4.js.gz
react_frontend/0c437fb7.js
react_frontend/0c437fb7.js.LICENSE.txt
react_frontend/0c437fb7.js.gz
react_frontend/0c63587a.js
react_frontend/0c63587a.js.LICENSE.txt
react_frontend/0c63587a.js.gz
react_frontend/0cd20209.js
react_frontend/0cd20209.js.LICENSE.txt
react_frontend/0cd20209.js.gz
react_frontend/0e22fbc6.js
react_frontend/0e22fbc6.js.LICENSE.txt
react_frontend/0e22fbc6.js.gz
react_frontend/0ee3b740.js
react_frontend/0ee3b740.js.gz
react_frontend/1119f07f.js
react_frontend/1119f07f.js.LICENSE.txt
react_frontend/1119f07f.js.gz
react_frontend/116bc9d9.js
react_frontend/116bc9d9.js.gz
react_frontend/11c1e42c.js
react_frontend/11c1e42c.js.LICENSE.txt
react_frontend/11c1e42c.js.gz
react_frontend/11d4d24c.js
react_frontend/11d4d24c.js.gz
react_frontend/11f36f2c.js
react_frontend/11f36f2c.js.gz
react_frontend/1237b6bd.js
react_frontend/1237b6bd.js.gz
react_frontend/14d5c526.js
react_frontend-20240625164333.dist-info/LICENSE
react_frontend-20240625164333.dist-info/METADATA
react_frontend-20240625164333.dist-info/WHEEL
react_frontend-20240625164333.dist-info/top_level.txt
react_frontend-20240625164333.dist-info/RECORD
