Metadata-Version: 2.1
Name: react-frontend
Version: 20240625164333
Summary: The React frontend
Home-page: https://github.com/gertjanstulp/ha-react-frontend
Author: Gertjan Stulp
Author-email: 
License-File: LICENSE
